{
  "type": "object",
  "properties": {
    "TabMode": {
      "type": "string",
      "title": "Tab Mode",
      "enum": [
        "standard",
        "simple",
        "navigation"
      ],
      "default": "standard"
    },
    "TabPosition": {
      "type": "string",
      "title": "Tab Position",
      "enum": [
        "top",
        "bottom",
        "vertical"
      ],
      "default": "top"
    },
    "TabAlignment": {
      "type": "string",
      "title": "Tab Alignment",
      "enum": [
        "left",
        "right",
        "centered",
        "justified"
      ],
      "default": "left"
    },
    "Color": {
      "type": "string",
      "title": "Tab Color",
      "enum": [
        "default",
        "primary",
        "secondary",
        "tertiary",
        "quaternary"
      ],
      "default": "default"
    },
    "TabIconMode": {
      "type": "string",
      "title": "Tab Icon Mode",
      "enum": [
        "default",
        "bigicons"
      ],
      "default": "default"
    }
  }
}